[{"framework_a":"CatBoost","framework_b":"XGBoost","metric":"f1_macro","diff":-0.0055569639,"t_stat":-5.1210891092,"p_value":0.006880926,"boot_ci_low":-0.0072587205,"boot_ci_high":-0.0034293791},{"framework_a":"CatBoost","framework_b":"XGBoost","metric":"accuracy","diff":-0.0147005302,"t_stat":-16.9464972366,"p_value":0.0000710913,"boot_ci_low":-0.0160930727,"boot_ci_high":-0.013123765},{"framework_a":"H2O_AutoML","framework_b":"leaderboard","metric":"f1_macro","diff":0.0,"t_stat":null,"p_value":null,"boot_ci_low":0.0,"boot_ci_high":0.0},{"framework_a":"H2O_AutoML","framework_b":"leaderboard","metric":"accuracy","diff":0.0,"t_stat":null,"p_value":null,"boot_ci_low":0.0,"boot_ci_high":0.0}]